Arrays in Java and Their Compilation
Arrays are a fundamental data structure in Java, and understanding how they are represented in source code and compiled bytecode is crucial for students learning about compilers or the Java Virtual Machine (JVM). This document discusses how arrays are defined and manipulated in Java, and how these operations are translated by the compiler into bytecode.

1. Java Source Code Example
Below is a simple Java program that demonstrates how to declare, initialize, and use an integer array:

public class ArrayEx {
    public static void main(String[] args) {
        int[] arr = new int[3];    // Array declaration and allocation
        arr[0] = 100;              // Assigning values
        arr[1] = 200;
        arr[2] = 300;

        for (int i = 0; i < arr.length; i++) {  // Accessing elements
            System.out.println("arr[" + i + "] = " + arr[i]);
        }
    }
}
Key Points:

int[] arr = new int[3]; creates an integer array of length 3.
Elements are accessed and assigned via indices (arr[0], arr[1], etc.).
arr.length gives the size of the array.
int[] arr = new int[3]; ↓ +--------+ +---------+---------+---------+ | arr |──────► | [0]=100 | [1]=200 | [2]=300 | +--------+ +---------+---------+---------+ Stack Heap (object: [I)

2. How the Compiler Translates Arrays
When the Java compiler (javac) compiles the above code, it generates Java bytecode. The bytecode instructions show how the JVM handles array operations.

javac ArrayEx.java

javap -c ArrayEx

Example: Decompiled Bytecode Output
Compiled from "ArrayEx.java"
public class ArrayEx {
  public ArrayEx();
    Code:
       0: aload_0
       1: invokespecial #1                  // Call Object constructor
       4: return

  public static void main(java.lang.String[]);
    Code:
       0: iconst_3                          // Push 3 onto stack (array length)
       1: newarray       int                // Create new int array
       3: astore_1                          // Store array reference in local variable 1
       4: aload_1
       5: iconst_0
       6: bipush        100
       8: iastore                           // arr[0] = 100
       9: aload_1
      10: iconst_1
      11: sipush        200
      14: iastore                           // arr[1] = 200
      15: aload_1
      16: iconst_2
      17: sipush        300
      20: iastore                           // arr[2] = 300
      21: iconst_0
      22: istore_2                          // int i = 0
      23: iload_2
      24: aload_1
      25: arraylength
      26: if_icmpge     50                  // if (i >= arr.length) goto 50
      29: getstatic     #7                  // Get System.out
      32: iload_2
      33: aload_1
      34: iload_2
      35: iaload                            // arr[i]
      36: invokedynamic #13,  0             // String concatenation
      41: invokevirtual #17                 // Println
      44: iinc          2, 1                // i++
      47: goto          23                  // Loop
      50: return
}
Explanation of Bytecode Instructions
iconst_3: Pushes the constant 3 onto the stack (the array size).
newarray int: Allocates a new integer array of the specified size.
astore_1: Stores the array reference in local variable 1.
aload_1, iconst_0, bipush 100, iastore: Sets arr[0] = 100.
arraylength: Retrieves the length of the array.
iaload/iastore: Loads or stores an int from/into the array.
for loop: Handled via loading/storing and conditional jumps.
invokedynamic: Used for string concatenation in recent Java versions.
3. Important Concepts Covered
Array Declaration and Instantiation: Compiled to newarray instruction.
Element Assignment and Access: iastore and iaload are used for integer arrays.
Array Length: Accessed via arraylength instruction.
Loops over Arrays: Managed with conditional jumps (if_icmpge, goto) and increment (iinc).
4. Summary Table: Java to Bytecode Mapping
Java Statement	Bytecode Instructions
int[] arr = new int[3];	iconst_3, newarray int, astore
arr[i] = value;	aload, iconst, value, iastore
value = arr[i];	aload, iconst, iaload, istore
arr.length	aload, arraylength, istore
5. Conclusion
Understanding how Java arrays are compiled into bytecode gives insight into:

How high-level data structures are implemented on the JVM.
The efficiency and limitations of array operations.
How the compiler translates familiar Java syntax into lower-level instructions executed by the JVM.
